{
  "1D_row": {
    "small_100x100": {
      "4": {
        "time": 0.0823,
        "speedup": 2.91,
        "efficiency": 0.728
      },
      "9": {
        "time": 0.0456,
        "speedup": 5.25,
        "efficiency": 0.583
      },
      "16": {
        "time": 0.0334,
        "speedup": 7.16,
        "efficiency": 0.448
      }
    },
    "medium_500x500": {
      "4": {
        "time": 1.845,
        "speedup": 3.12,
        "efficiency": 0.78
      },
      "9": {
        "time": 0.987,
        "speedup": 5.83,
        "efficiency": 0.648
      },
      "16": {
        "time": 0.623,
        "speedup": 9.24,
        "efficiency": 0.578
      }
    },
    "large_1000x1000": {
      "4": {
        "time": 7.234,
        "speedup": 3.24,
        "efficiency": 0.81
      },
      "9": {
        "time": 3.678,
        "speedup": 6.37,
        "efficiency": 0.708
      },
      "16": {
        "time": 2.145,
        "speedup": 10.92,
        "efficiency": 0.683
      }
    }
  },
  "2D_block": {
    "small_100x100": {
      "4": {
        "time": 0.0745,
        "speedup": 3.21,
        "efficiency": 0.803
      },
      "9": {
        "time": 0.0389,
        "speedup": 6.15,
        "efficiency": 0.683
      },
      "16": {
        "time": 0.0267,
        "speedup": 8.96,
        "efficiency": 0.56
      }
    },
    "medium_500x500": {
      "4": {
        "time": 1.623,
        "speedup": 3.54,
        "efficiency": 0.886
      },
      "9": {
        "time": 0.812,
        "speedup": 7.08,
        "efficiency": 0.787
      },
      "16": {
        "time": 0.478,
        "speedup": 12.03,
        "efficiency": 0.752
      }
    },
    "large_1000x1000": {
      "4": {
        "time": 6.345,
        "speedup": 3.69,
        "efficiency": 0.923
      },
      "9": {
        "time": 2.987,
        "speedup": 7.84,
        "efficiency": 0.871
      },
      "16": {
        "time": 1.634,
        "speedup": 14.33,
        "efficiency": 0.896
      }
    }
  }
}